<?xml version="1.0" ?>
<annotation>
   <folder>EmojiDataset</folder>
   <filename>Emojis_3_Image401</filename>
   <path>labels/Emojis_3_Image401</path>
   <source>
      <database>Unspecified</database>
   </source>
   <size>
      <width>640</width>
      <height>480</height>
      <depth>3</depth>
   </size>
   <object>
      <name>wow</name>
      <pose>Unspecified</pose>
      <truncated>0</truncated>
      <difficult>0</difficult>
      <bndbox>
         <xmin>12</xmin>
         <ymin>5</ymin>
         <xmax>187</xmax>
         <ymax>180</ymax>
      </bndbox>
   </object>
   <object>
      <name>wow</name>
      <pose>Unspecified</pose>
      <truncated>0</truncated>
      <difficult>0</difficult>
      <bndbox>
         <xmin>210</xmin>
         <ymin>6</ymin>
         <xmax>372</xmax>
         <ymax>168</ymax>
      </bndbox>
   </object>
   <object>
      <name>haha</name>
      <pose>Unspecified</pose>
      <truncated>0</truncated>
      <difficult>0</difficult>
      <bndbox>
         <xmin>543</xmin>
         <ymin>0</ymin>
         <xmax>640</xmax>
         <ymax>133</ymax>
      </bndbox>
   </object>
</annotation>
