<?xml version="1.0" ?>
<annotation>
   <folder>EmojiDataset</folder>
   <filename>Emojis_1_Image783</filename>
   <path>labels/Emojis_1_Image783</path>
   <source>
      <database>Unspecified</database>
   </source>
   <size>
      <width>640</width>
      <height>480</height>
      <depth>3</depth>
   </size>
   <object>
      <name>care</name>
      <pose>Unspecified</pose>
      <truncated>0</truncated>
      <difficult>0</difficult>
      <bndbox>
         <xmin>436</xmin>
         <ymin>234</ymin>
         <xmax>576</xmax>
         <ymax>374</ymax>
      </bndbox>
   </object>
</annotation>
