<?xml version="1.0" ?>
<annotation>
   <folder>EmojiDataset</folder>
   <filename>Emojis_1_Image273</filename>
   <path>labels/Emojis_1_Image273</path>
   <source>
      <database>Unspecified</database>
   </source>
   <size>
      <width>640</width>
      <height>449</height>
      <depth>3</depth>
   </size>
   <object>
      <name>like</name>
      <pose>Unspecified</pose>
      <truncated>0</truncated>
      <difficult>0</difficult>
      <bndbox>
         <xmin>462</xmin>
         <ymin>252</ymin>
         <xmax>587</xmax>
         <ymax>377</ymax>
      </bndbox>
   </object>
</annotation>
