<?xml version="1.0" ?>
<annotation>
   <folder>EmojiDataset</folder>
   <filename>Emojis_1_Image337</filename>
   <path>labels/Emojis_1_Image337</path>
   <source>
      <database>Unspecified</database>
   </source>
   <size>
      <width>640</width>
      <height>361</height>
      <depth>3</depth>
   </size>
   <object>
      <name>wow</name>
      <pose>Unspecified</pose>
      <truncated>0</truncated>
      <difficult>0</difficult>
      <bndbox>
         <xmin>368</xmin>
         <ymin>96</ymin>
         <xmax>508</xmax>
         <ymax>236</ymax>
      </bndbox>
   </object>
</annotation>
