<?xml version="1.0" ?>
<annotation>
   <folder>EmojiDataset</folder>
   <filename>Emojis_1_Image834</filename>
   <path>labels/Emojis_1_Image834</path>
   <source>
      <database>Unspecified</database>
   </source>
   <size>
      <width>640</width>
      <height>427</height>
      <depth>3</depth>
   </size>
   <object>
      <name>love</name>
      <pose>Unspecified</pose>
      <truncated>0</truncated>
      <difficult>0</difficult>
      <bndbox>
         <xmin>354</xmin>
         <ymin>162</ymin>
         <xmax>449</xmax>
         <ymax>257</ymax>
      </bndbox>
   </object>
</annotation>
